anyio_atexit-1.0.0.dist-info/METADATA
anyio_atexit-1.0.0.dist-info/WHEEL
anyio_atexit-1.0.0.dist-info/entry_points.txt
anyio_atexit-1.0.0.dist-info/licenses/LICENSE
anyio_atexit/__init__.py
anyio_atexit/callback.py
anyio_atexit/py.typed
anyio_atexit-1.0.0.dist-info/RECORD
