Metadata-Version: 2.4
Name: anyio-atexit
Version: 1.0.0
Summary: Small AnyIO utility for ensuring some task runs before the current async context finishes.
Author-Email: Elias Gabriel <oss@eliasfgabriel.com>
License-Expression: BSD-3-Clause-Clear
License-File: LICENSE
Classifier: Development Status :: 5 - Production/Stable
Classifier: Intended Audience :: Developers
Classifier: Framework :: AnyIO
Classifier: Framework :: AsyncIO
Classifier: Framework :: Trio
Classifier: Typing :: Typed
Classifier: Topic :: Utilities
Classifier: Programming Language :: Python
Classifier: Programming Language :: Python :: 3
Classifier: Programming Language :: Python :: 3.8
Classifier: Programming Language :: Python :: 3.9
Classifier: Programming Language :: Python :: 3.10
Classifier: Programming Language :: Python :: 3.11
Classifier: Programming Language :: Python :: 3.12
Classifier: Programming Language :: Python :: 3.13
Project-URL: homepage, https://github.com/thearchitector/anyio-atexit
Project-URL: source, https://github.com/thearchitector/anyio-atexit
Project-URL: changelog, https://github.com/thearchitector/anyio-atexit/releases
Project-URL: issues, https://github.com/thearchitector/anyio-atexit/issues
Requires-Python: >=3.8
Requires-Dist: sniffio>=1.1
Provides-Extra: trio
Requires-Dist: trio>=0.23.0; extra == "trio"
Provides-Extra: asyncio
Requires-Dist: asyncio-atexit>=1.0.1; extra == "asyncio"
